hatch_pip_compile/__about__.py
hatch_pip_compile/__init__.py
hatch_pip_compile/__main__.py
hatch_pip_compile/base.py
hatch_pip_compile/cli.py
hatch_pip_compile/exceptions.py
hatch_pip_compile/hooks.py
hatch_pip_compile/installer.py
hatch_pip_compile/lock.py
hatch_pip_compile/plugin.py
hatch_pip_compile/py.typed
hatch_pip_compile/resolver.py
hatch_pip_compile-1.11.5.dist-info/METADATA
hatch_pip_compile-1.11.5.dist-info/WHEEL
hatch_pip_compile-1.11.5.dist-info/entry_points.txt
hatch_pip_compile-1.11.5.dist-info/licenses/LICENSE
hatch_pip_compile-1.11.5.dist-info/RECORD
