Metadata-Version: 2.4
Name: hatch-pip-compile
Version: 1.11.5
Summary: hatch plugin to use pip-compile to manage project dependencies
Project-URL: Documentation, https://juftin.github.io/hatch-pip-compile
Project-URL: Issues, https://juftin.github.io/hatch-pip-compile/issues
Project-URL: Source, https://github.com/juftin/hatch-pip-compile
Author-email: Justin Flannery <juftin@juftin.com>
License-Expression: MIT
License-File: LICENSE
Classifier: Development Status :: 3 - Alpha
Classifier: Framework :: Hatch
Classifier: Operating System :: OS Independent
Classifier: Programming Language :: Python
Classifier: Programming Language :: Python :: 3.8
Classifier: Programming Language :: Python :: 3.9
Classifier: Programming Language :: Python :: 3.10
Classifier: Programming Language :: Python :: 3.11
Classifier: Programming Language :: Python :: 3.12
Classifier: Programming Language :: Python :: Implementation :: CPython
Classifier: Programming Language :: Python :: Implementation :: PyPy
Requires-Python: >=3.8
Requires-Dist: click
Requires-Dist: hatch<2,>=1.7.0
Requires-Dist: pip-tools>=6
Requires-Dist: rich
